{
  "annotations": {
    "list": [
      {
        "builtIn": 1,
        "datasource": "-- Grafana --",
        "enable": true,
        "hide": true,
        "iconColor": "rgba(0, 211, 255, 1)",
        "name": "Annotations & Alerts",
        "type": "dashboard"
      }
    ]
  },
  "editable": true,
  "gnetId": null,
  "graphTooltip": 0,
  "id": 1,
  "links": [],
  "panels": [
    {
      "aliasColors": {},
      "bars": false,
      "dashLength": 10,
      "dashes": false,
      "datasource": "PostgreSQL",
      "fill": 1,
      "gridPos": {
        "h": 9,
        "w": 12,
        "x": 0,
        "y": 0
      },
      "id": 8,
      "legend": {
        "avg": false,
        "current": false,
        "hideEmpty": false,
        "hideZero": false,
        "max": false,
        "min": false,
        "show": false,
        "total": false,
        "values": false
      },
      "lines": false,
      "linewidth": 2,
      "links": [],
      "nullPointMode": "null as zero",
      "percentage": false,
      "pointradius": 5,
      "points": true,
      "renderer": "flot",
      "seriesOverrides": [],
      "spaceLength": 10,
      "stack": false,
      "steppedLine": false,
      "targets": [
        {
          "expr": "",
          "format": "time_series",
          "group": [],
          "intervalFactor": 1,
          "metricColumn": "none",
          "rawQuery": true,
          "rawSql": "SELECT\n  --created_at AS \"time\",\n  $__timeGroup(\"created_at\",'10s'),\n  count(id)\nFROM possible_frauds\nWHERE $__timeFilter(created_at)\nGROUP BY time",
          "refId": "A",
          "select": [
            [
              {
                "params": [
                  "total_amount"
                ],
                "type": "column"
              }
            ]
          ],
          "table": "possible_frauds",
          "timeColumn": "created_at",
          "timeColumnType": "timestamp",
          "where": [
            {
              "name": "$__timeFilter",
              "params": [],
              "type": "macro"
            }
          ]
        }
      ],
      "thresholds": [],
      "timeFrom": null,
      "timeRegions": [],
      "timeShift": null,
      "title": "Possible Fraud",
      "tooltip": {
        "shared": true,
        "sort": 0,
        "value_type": "individual"
      },
      "type": "graph",
      "xaxis": {
        "buckets": null,
        "mode": "time",
        "name": null,
        "show": true,
        "values": []
      },
      "yaxes": [
        {
          "format": "short",
          "label": "Count",
          "logBase": 1,
          "max": null,
          "min": "0",
          "show": true
        },
        {
          "format": "short",
          "label": "",
          "logBase": 1,
          "max": null,
          "min": null,
          "show": true
        }
      ],
      "yaxis": {
        "align": false,
        "alignLevel": null
      }
    },
    {
      "columns": [],
      "datasource": "PostgreSQL",
      "fontSize": "100%",
      "gridPos": {
        "h": 9,
        "w": 12,
        "x": 12,
        "y": 0
      },
      "hideTimeOverride": false,
      "id": 10,
      "links": [],
      "pageSize": null,
      "scroll": true,
      "showHeader": true,
      "sort": {
        "col": 0,
        "desc": true
      },
      "styles": [
        {
          "alias": "Time",
          "dateFormat": "YYYY-MM-DD HH:mm:ss",
          "link": false,
          "linkTargetBlank": false,
          "linkUrl": "",
          "pattern": "Time",
          "type": "date"
        },
        {
          "alias": "",
          "colorMode": null,
          "colors": [
            "rgba(245, 54, 54, 0.9)",
            "rgba(237, 129, 40, 0.89)",
            "rgba(50, 172, 45, 0.97)"
          ],
          "decimals": 0,
          "link": false,
          "linkTargetBlank": true,
          "linkTooltip": "",
          "linkUrl": "",
          "pattern": "id",
          "thresholds": [
            ""
          ],
          "type": "number",
          "unit": "short"
        },
        {
          "alias": "Name",
          "colorMode": null,
          "colors": [
            "rgba(245, 54, 54, 0.9)",
            "rgba(237, 129, 40, 0.89)",
            "rgba(50, 172, 45, 0.97)"
          ],
          "dateFormat": "YYYY-MM-DD HH:mm:ss",
          "decimals": 2,
          "mappingType": 1,
          "pattern": "name",
          "preserveFormat": false,
          "sanitize": false,
          "thresholds": [],
          "type": "string",
          "unit": "short"
        },
        {
          "alias": "",
          "colorMode": null,
          "colors": [
            "rgba(245, 54, 54, 0.9)",
            "rgba(237, 129, 40, 0.89)",
            "rgba(50, 172, 45, 0.97)"
          ],
          "dateFormat": "YYYY-MM-DD HH:mm:ss",
          "decimals": 2,
          "mappingType": 1,
          "pattern": "Created Time",
          "thresholds": [],
          "type": "date",
          "unit": "short"
        }
      ],
      "targets": [
        {
          "expr": "",
          "format": "table",
          "group": [],
          "intervalFactor": 1,
          "metricColumn": "none",
          "rawQuery": true,
          "rawSql": "SELECT id AS \"Id\", name AS \"Name\", credit_card AS \"Credit Card\", total_amount AS \"Total Amount\", transaction_count As \"Transaction Count\", created_at AS \"Created Time\" \nFROM public.possible_frauds\nWHERE $__timeFilter(created_at)",
          "refId": "A",
          "select": [
            [
              {
                "params": [
                  "value"
                ],
                "type": "column"
              }
            ]
          ],
          "timeColumn": "time",
          "where": [
            {
              "name": "$__timeFilter",
              "params": [],
              "type": "macro"
            }
          ]
        }
      ],
      "title": "Possible Fraud Data",
      "transform": "table",
      "transparent": false,
      "type": "table"
    },
    {
      "aliasColors": {},
      "bars": false,
      "dashLength": 10,
      "dashes": false,
      "decimals": null,
      "fill": 1,
      "gridPos": {
        "h": 9,
        "w": 24,
        "x": 0,
        "y": 9
      },
      "id": 4,
      "legend": {
        "alignAsTable": false,
        "avg": false,
        "current": false,
        "hideEmpty": false,
        "hideZero": false,
        "max": false,
        "min": false,
        "rightSide": false,
        "show": true,
        "total": false,
        "values": false
      },
      "lines": true,
      "linewidth": 2,
      "links": [],
      "nullPointMode": "connected",
      "percentage": false,
      "pointradius": 5,
      "points": false,
      "renderer": "flot",
      "seriesOverrides": [],
      "spaceLength": 10,
      "stack": false,
      "steppedLine": false,
      "targets": [
        {
          "expr": "sum(kafka_server_brokertopicmetrics_messagesin_total{instance=~\"10.100.*.200:7071\",job=\"kafka\",topic=\"dbserver1.public.transactions\"})",
          "format": "time_series",
          "hide": true,
          "intervalFactor": 1,
          "legendFormat": "dbserver1.public.transactions",
          "refId": "A"
        },
        {
          "expr": "sum(kafka_server_brokertopicmetrics_messagesin_total{instance=~\"10.100.*.200:7071\",job=\"kafka\",topic=\"FLATTEN_TRANSACTIONS\"})",
          "format": "time_series",
          "hide": true,
          "intervalFactor": 1,
          "legendFormat": "FLATTEN_TRANSACTIONS",
          "refId": "B"
        },
        {
          "expr": "sum without(instance)(rate(kafka_server_brokertopicmetrics_messagesin_total{job=\"kafka\",topic=\"dbserver1.public.transactions\"}[5m]))",
          "format": "time_series",
          "intervalFactor": 1,
          "legendFormat": "{{topic}}",
          "refId": "C"
        },
        {
          "expr": "sum without(instance)(rate(kafka_server_brokertopicmetrics_messagesin_total{job=\"kafka\",topic=\"FLATTEN_TRANSACTIONS\"}[5m]))",
          "format": "time_series",
          "intervalFactor": 1,
          "legendFormat": "{{topic}}",
          "refId": "D"
        }
      ],
      "thresholds": [],
      "timeFrom": null,
      "timeRegions": [],
      "timeShift": null,
      "title": "Transactions",
      "tooltip": {
        "shared": true,
        "sort": 0,
        "value_type": "individual"
      },
      "transparent": false,
      "type": "graph",
      "xaxis": {
        "buckets": null,
        "mode": "time",
        "name": null,
        "show": true,
        "values": []
      },
      "yaxes": [
        {
          "decimals": null,
          "format": "short",
          "label": "Messages/s",
          "logBase": 1,
          "max": null,
          "min": null,
          "show": true
        },
        {
          "format": "short",
          "label": null,
          "logBase": 1,
          "max": null,
          "min": null,
          "show": true
        }
      ],
      "yaxis": {
        "align": false,
        "alignLevel": null
      }
    }
  ],
  "refresh": "5s",
  "schemaVersion": 16,
  "style": "dark",
  "tags": [],
  "templating": {
    "list": []
  },
  "time": {
    "from": "now-6h",
    "to": "now"
  },
  "timepicker": {
    "refresh_intervals": [
      "5s",
      "10s",
      "30s",
      "1m",
      "5m",
      "15m",
      "30m",
      "1h",
      "2h",
      "1d"
    ],
    "time_options": [
      "5m",
      "15m",
      "1h",
      "6h",
      "12h",
      "24h",
      "2d",
      "7d",
      "30d"
    ]
  },
  "timezone": "",
  "title": "Streaming",
  "uid": "g3k69Duik",
  "version": 5
}
